{
  "build": {
    "development": {
      "developmentClient": true,
      "distribution": "internal",
      "ios": {
        "credentialsSource": "remote",
        "cocoapods": "1.15.2"
      }
    },
    "preview": {
      "distribution": "internal",
      "ios": {
        "credentialsSource": "remote",
        "cocoapods": "1.15.2"
      },
      "android": {
        "credentialsSource": "remote"
      }
    },
    "production": {
      "distribution": "store",
      "ios": {
        "credentialsSource": "remote",
        "cocoapods": "1.15.2"
      },
      "android": {
        "credentialsSource": "remote"
      }
    }
  }
}
